{
    "preset": "psr12",
    "rules": {
        "declare_strict_types": true,
        "final_class": true,
        "array_indentation": true,
        "array_syntax": {
            "syntax": "short"
        },
        "blank_line_after_namespace": true,
        "blank_line_after_opening_tag": true,
        "blank_lines_before_namespace": true,
        "trailing_comma_in_multiline": true,
        "no_unused_imports": true,
        "ordered_imports": {
            "sort_algorithm": "alpha"
        },
        "single_quote": true,
        "no_trailing_whitespace": true,
        "no_trailing_whitespace_in_comment": true,
        "phpdoc_trim": true,
        "no_empty_phpdoc": true,
        "binary_operator_spaces": {
            "default": "single_space"
        },
        "cast_spaces": {
            "space": "single"
        },
        "concat_space": {
            "spacing": "one"
        },
        "arrow_function_spaces": true,
        "strict_comparison": true,
        "no_superfluous_elseif": true,
        "no_useless_else": true,
        "return_assignment": true
    }
}
